{
    "customTemplates": [
		{
			"name": "page-no-title",
			"postTypes": [
				"page"
			],
			"title": "Page: No Title"
		}
	],
	"settings": {
		"appearanceTools": true,
		"color": {
			"defaultPalette": false,
			"palette": [
				{
					"color": "#223201",
					"name": "Pistachio 950",
					"slug": "custom-primary-950"
				},
				{
					"color": "#41580f",
					"name": "Pistachio 900",
					"slug": "custom-primary-900"
				},
				{
					"color": "#4f690b",
					"name": "Pistachio 800",
					"slug": "custom-primary-800"
				},
				{
					"color": "#628506",
					"name": "Pistachio 700",
					"slug": "custom-primary-700"
				},
				{
					"color": "#8aba00",
					"name": "Pistachio 600",
					"slug": "custom-primary-600"
				},
				{
					"color": "#a8dc06",
					"name": "Pistachio 500",
					"slug": "custom-primary-500"
				},
				{
					"color": "#c7f526",
					"name": "Pistachio 400",
					"slug": "custom-primary-400"
				},
				{
					"color": "#dbfe58",
					"name": "Pistachio 300",
					"slug": "custom-primary-300"
				},
				{
					"color": "#ebff95",
					"name": "Pistachio 200",
					"slug": "custom-primary-200"
				},
				{
					"color": "#f6ffc7",
					"name": "Pistachio 100",
					"slug": "custom-primary-100"
				},
				{
					"color": "#fcffe5",
					"name": "Pistachio 50",
					"slug": "custom-primary-50"
				},
				{
					"color": "#ff7268",
					"name": "Milano Red 600",
					"slug": "custom-primary-hover"
				},
				{
					"color": "#141418",
					"name": "Black 1100",
					"slug": "custom-black-1100"
				},
				{
					"color": "#16171C",
					"name": "Black 1000",
					"slug": "custom-black-1000"
				},
				{
					"color": "#18191f",
					"name": "Black 950",
					"slug": "custom-black-950"
				},
				{
					"color": "#353845",
					"name": "Black 900",
					"slug": "custom-black-900"
				},
				{
					"color": "#3c4050",
					"name": "Black 800",
					"slug": "custom-black-800"
				},
				{
					"color": "#454a5f",
					"name": "Black 700",
					"slug": "custom-black-700"
				},
				{
					"color": "#555b74",
					"name": "Black 600",
					"slug": "custom-black-600"
				},
				{
					"color": "#6a728d",
					"name": "Black 500",
					"slug": "custom-black-500"
				},
				{
					"color": "#8990a7",
					"name": "Black 400",
					"slug": "custom-black-400"
				},
				{
					"color": "#b2b6c7",
					"name": "Black 300",
					"slug": "custom-black-300"
				},
				{
					"color": "#d6d8e1",
					"name": "Black 200",
					"slug": "custom-black-200"
				},
				{
					"color": "#ededf1",
					"name": "Black 100",
					"slug": "custom-black-100"
				},
				{
					"color": "#f6f7f9",
					"name": "Black 50",
					"slug": "custom-black-50"
				},
				{
					"color": "#000",
					"name": "True Black",
					"slug": "custom-black-true"
				},
				{
					"color": "#ffffff",
					"name": "White",
					"slug": "custom-white"
				}
			]
		},
		"layout": {
			"contentSize": "768px",
			"wideSize": "1024px"
		},
		"typography": {
			"defaultFontSizes": false,
			"fontFamilies": [
				{
					"fontFace": [
						{
							"fontFamily": "\"Work Sans\"",
							"fontStyle": "normal",
							"fontWeight": "400",
							"src": [
								"file:./assets/fonts/work-sans/work-sans-400-normal.woff2"
							]
						},
						{
							"fontFamily": "\"Work Sans\"",
							"fontStyle": "italic",
							"fontWeight": "400",
							"src": [
								"file:./assets/fonts/work-sans/work-sans-400-italic.woff2"
							]
						},
						{
							"fontFamily": "\"Work Sans\"",
							"fontStyle": "normal",
							"fontWeight": "300",
							"src": [
								"file:./assets/fonts/work-sans/work-sans-300-normal.woff2"
							]
						},
						{
							"fontFamily": "\"Work Sans\"",
							"fontStyle": "normal",
							"fontWeight": "500",
							"src": [
								"file:./assets/fonts/work-sans/work-sans-500-normal.woff2"
							]
						},
						{
							"fontFamily": "\"Work Sans\"",
							"fontStyle": "normal",
							"fontWeight": "700",
							"src": [
								"file:./assets/fonts/work-sans/work-sans-700-normal.woff2"
							]
						},
						{
							"fontFamily": "\"Work Sans\"",
							"fontStyle": "italic",
							"fontWeight": "300",
							"src": [
								"file:./assets/fonts/work-sans/work-sans-300-italic.woff2"
							]
						},
						{
							"fontFamily": "\"Work Sans\"",
							"fontStyle": "italic",
							"fontWeight": "500",
							"src": [
								"file:./assets/fonts/work-sans/work-sans-500-italic.woff2"
							]
						},
						{
							"fontFamily": "\"Work Sans\"",
							"fontStyle": "italic",
							"fontWeight": "700",
							"src": [
								"file:./assets/fonts/work-sans/work-sans-700-italic.woff2"
							]
						}
					],
					"fontFamily": "\"Work Sans\", sans-serif",
					"name": "Work Sans",
					"slug": "work-sans"
				}
			],
			"fontSizes": [
				{
					"fluid": {
						"max": "16px",
						"min": "14px"
					},
					"name": "Small",
					"size": "16px",
					"slug": "small"
				},
				{
					"fluid": {
						"max": "20px",
						"min": "16px"
					},
					"name": "Medium",
					"size": "20px",
					"slug": "medium"
				},
				{
					"fluid": {
						"max": "24px",
						"min": "20px"
					},
					"name": "Large",
					"size": "24px",
					"slug": "large"
				},
				{
					"fluid": {
						"max": "32px",
						"min": "24px"
					},
					"name": "X-Large",
					"size": "32px",
					"slug": "x-large"
				},
				{
					"fluid": {
						"max": "36px",
						"min": "28px"
					},
					"name": "2X-Large",
					"size": "36px",
					"slug": "xx-large"
				},
				{
					"fluid": {
						"max": "44px",
						"min": "32px"
					},
					"name": "3X-Large",
					"size": "44px",
					"slug": "xxx-large"
				},
				{
					"fluid": {
						"max": "48px",
						"min": "40px"
					},
					"name": "4X-Large",
					"size": "48px",
					"slug": "custom-1"
				}
			]
		}
	},
	"styles": {
		"blocks": {
			"core/quote": {
				"border": {
					"color": null,
					"left": {
						"color": "var(--wp--preset--color--light-yellow)",
						"style": "solid",
						"width": "3px"
					},
					"style": null,
					"width": null
				},
				"spacing": {
					"blockGap": "var(--wp--preset--spacing--20)",
					"margin": {
						"left": "0",
						"right": "0"
					},
					"padding": {
						"bottom": "var(--wp--preset--spacing--20)",
						"left": "var(--wp--preset--spacing--50)",
						"right": "0",
						"top": "var(--wp--preset--spacing--20)"
					}
				}
			}
		},
		"color": {
			"background": "var(--wp--preset--color--custom-black-950)",
			"text": "var(--wp--preset--color--custom-black-100)"
		},
		"elements": {
			"button": {
				"color": {
					"background": "var(--wp--preset--color--custom-primary-400)",
					"text": "var(--wp--preset--color--custom-black-true)"
				},
				"typography": {
					"fontSize": "var(--wp--preset--font-size--small)"
				}
			},
			"caption": {
				"color": {
					"text": "var(--wp--preset--color--custom-black-50)"
				},
				"typography": {
					"fontSize": "var(--wp--preset--font-size--small)",
					"fontStyle": "italic",
					"fontWeight": "300"
				}
			},
			"h1": {
				"typography": {
					"fontSize": "var(--wp--preset--font-size--xxx-large)",
					"lineHeight": "1.2"
				}
			},
			"h2": {
				"typography": {
					"fontSize": "var(--wp--preset--font-size--xx-large)"
				}
			},
			"h3": {
				"typography": {
					"fontSize": "28px"
				}
			},
			"h4": {
				"typography": {
					"fontSize": "var(--wp--preset--font-size--large)"
				}
			},
			"h5": {
				"typography": {
					"fontSize": "var(--wp--preset--font-size--medium)"
				}
			},
			"h6": {
				"typography": {
					"fontSize": "var(--wp--preset--font-size--medium)",
					"fontStyle": "italic",
					"fontWeight": "300"
				}
			},
			"heading": {
				"color": {
					"text": "var(--wp--preset--color--custom-black-100)"
				},
				"typography": {
					"fontFamily": "var(--wp--preset--font-family--work-sans)",
					"fontStyle": "normal",
					"fontWeight": "500",
					"lineHeight": 1.4
				}
			},
			"link": {
				":hover": {
					"color": {
						"text": "var(--wp--preset--color--custom-primary-400)"
					}
				},
				"color": {
					"text": "var(--wp--preset--color--custom-primary-200)"
				},
				"typography": {
					"fontFamily": "var(--wp--preset--font-family--work-sans)",
					"fontStyle": "normal",
					"fontWeight": "300",
					"textDecoration": "none"
				}
			}
		},
		"spacing": {
			"blockGap": "24px"
		},
		"typography": {
			"fontFamily": "var(--wp--preset--font-family--work-sans)",
			"fontSize": "var(--wp--preset--font-size--medium)",
			"fontStyle": "normal",
			"fontWeight": "300",
			"lineHeight": "1.7"
		}
	},
	"templateParts": [
		{
			"area": "header",
			"name": "header",
			"title": "Header"
		},
		{
			"area": "footer",
			"name": "footer",
			"title": "Footer"
		}
	],
	"version": 3,
	"$schema": "https://schemas.wp.org/wp/6.8/theme.json"
}